mtproxy/__init__.py
mtproxy/__main__.py
mtproxy/config.py
mtproxy/mtproto/__init__.py
mtproxy/mtproto/crypto.py
mtproxy/mtproto/data_center.py
mtproxy/mtproto/keys.py
mtproxy/proxy/__init__.py
mtproxy/proxy/connection_handler.py
mtproxy/proxy/proxy.py
mtproxy/proxy/streams/__init__.py
mtproxy/proxy/streams/base_stream_protocol.py
mtproxy/proxy/streams/client_steam_protocol.py
mtproxy/proxy/streams/server_steam_protocol.py
mtproxy/proxy/streams/wappers/__init__.py
mtproxy/proxy/streams/wappers/base_stream_reader.py
mtproxy/proxy/streams/wappers/base_stream_writer.py
mtproxy/proxy/streams/wappers/crypto_stream_reader.py
mtproxy/proxy/streams/wappers/crypto_stream_writer.py
mtproxy/utils/__init__.py
mtproxy/utils/async_tools.py
mtproxy/utils/ext.py
mtproxy/utils/ip_info.py
mtproxy/utils/socket_settings.py
mtproxy/utils/user.py
MTProxy-0.1.3.dist-info/LICENSE
MTProxy-0.1.3.dist-info/METADATA
MTProxy-0.1.3.dist-info/WHEEL
MTProxy-0.1.3.dist-info/entry_points.txt
MTProxy-0.1.3.dist-info/top_level.txt
MTProxy-0.1.3.dist-info/RECORD
