Metadata-Version: 2.1
Name: MTProxy
Version: 0.1.3
Summary: Async Python MTProto Proxy 
Home-page: http://github.com/i-Naji/mtproxy
Author: Naji
License: MIT
Keywords: mtproto proxy async asynchronous
Platform: UNKNOWN
Classifier: Development Status :: 4 - Beta
Classifier: Environment :: Console
Classifier: Framework :: AsyncIO
Classifier: Intended Audience :: Developers
Classifier: License :: OSI Approved :: MIT License
Classifier: Operating System :: POSIX :: Linux
Classifier: Operating System :: MacOS :: MacOS X
Classifier: Operating System :: Microsoft :: Windows
Classifier: Programming Language :: Python :: 3 :: Only
Classifier: Programming Language :: Python :: 3.5
Classifier: Programming Language :: Python :: 3.6
Classifier: Programming Language :: Python :: 3.7
Classifier: Topic :: Internet :: Proxy Servers
Requires-Python: >=3.5
Requires-Dist: cryptography
Provides-Extra: fast
Requires-Dist: uvloop ; extra == 'fast'
